{
  "name": "images/1723558284751_81cmJlbtx2L._SL1500_.jpg",
  "bucket": "jainco.appspot.com",
  "metageneration": 1,
  "generation": 1723558284791,
  "contentType": "image/jpeg",
  "storageClass": "STANDARD",
  "contentDisposition": "inline",
  "downloadTokens": [
    "ea258733-76a5-419c-8445-1c3c13d5896a"
  ],
  "etag": "8u6dcelsZ7MevmPX7HTSrS0GMqM",
  "customMetadata": {},
  "timeCreated": "2024-08-13T14:11:24.791Z",
  "updated": "2024-08-13T14:11:24.791Z",
  "size": 271110,
  "md5Hash": "XWthLy8QxNW9nTqlUeRrbg==",
  "crc32c": "978524200"
}