{
  "name": "images/1723485812455_rakshabandhan-pic-1.jpg",
  "bucket": "jainco.appspot.com",
  "metageneration": 1,
  "generation": 1723485812490,
  "contentType": "image/jpeg",
  "storageClass": "STANDARD",
  "contentDisposition": "inline",
  "downloadTokens": [
    "645d1aef-acb6-40b3-8bc8-af15bbdfa378"
  ],
  "etag": "ISgScHRMDxZVopYg/4FOsGE+exc",
  "customMetadata": {},
  "timeCreated": "2024-08-12T18:03:32.491Z",
  "updated": "2024-08-12T18:03:32.491Z",
  "size": 197171,
  "md5Hash": "keAihEGxDH5IGCDht8qcdw==",
  "crc32c": "4246373370"
}